[
  {
    "name": "Logeshwaran B",
    "email": "teros7023@gmail.com",
    "phone": "9365782104",
    "timestamp": "2026-06-11T05:12:44.606600"
  },
  {
    "name": "Logeshwaran B",
    "email": "teros7023@gmail.com",
    "phone": "9365782104",
    "timestamp": "2026-06-11T05:58:17.207773"
  },
  {
    "name": "Logeshwaran B",
    "email": "teros7023@gmail.com",
    "phone": "9365782104",
    "timestamp": "2026-06-11T07:03:43.199897"
  },
  {
    "name": "Logeshwaran B",
    "email": "teros7023@gmail.com",
    "phone": "9365782104",
    "timestamp": "2026-06-11T07:28:30.616947"
  },
  {
    "name": "Logeshwaran B",
    "email": "teros7023@gmail.com",
    "phone": "9365782104",
    "timestamp": "2026-06-11T13:26:30.167807"
  },
  {
    "name": "Logeshwaran B",
    "email": "teros7023@gmail.com",
    "phone": "9365782104",
    "timestamp": "2026-06-15T05:17:07.585874"
  },
  {
    "name": "Logeshwaran B",
    "email": "teros7023@gmail.com",
    "phone": "9365782104",
    "timestamp": "2026-06-15T05:31:43.956608"
  },
  {
    "name": "Logeshwaran B",
    "email": "teros7023@gmail.com",
    "phone": "9365782104",
    "timestamp": "2026-06-15T05:34:51.244146"
  },
  {
    "name": "Logeshwaran B",
    "email": "teros7023@gmail.com",
    "phone": "9365782104",
    "timestamp": "2026-06-15T05:37:11.862945"
  },
  {
    "name": "Logeshwaran B",
    "email": "teros7023@gmail.com",
    "phone": "9365782104",
    "timestamp": "2026-06-15T05:38:57.324881"
  },
  {
    "name": "siva",
    "email": "teros7023@gmail.com",
    "phone": "9365782104",
    "timestamp": "2026-06-16T05:31:10.011604"
  }
]